odoo/addons/maintenance_equipment_image/README.rst
odoo/addons/maintenance_equipment_image/__init__.py
odoo/addons/maintenance_equipment_image/__manifest__.py
odoo/addons/maintenance_equipment_image/i18n/es.po
odoo/addons/maintenance_equipment_image/i18n/fr.po
odoo/addons/maintenance_equipment_image/i18n/it.po
odoo/addons/maintenance_equipment_image/i18n/maintenance_equipment_image.pot
odoo/addons/maintenance_equipment_image/i18n/pt.po
odoo/addons/maintenance_equipment_image/models/__init__.py
odoo/addons/maintenance_equipment_image/models/maintenance_equipment.py
odoo/addons/maintenance_equipment_image/readme/CONTRIBUTORS.rst
odoo/addons/maintenance_equipment_image/readme/DESCRIPTION.rst
odoo/addons/maintenance_equipment_image/static/description/icon.png
odoo/addons/maintenance_equipment_image/static/description/index.html
odoo/addons/maintenance_equipment_image/views/maintenance_equipment_views.xml
odoo_addon_maintenance_equipment_image-16.0.1.0.0.9.dist-info/METADATA
odoo_addon_maintenance_equipment_image-16.0.1.0.0.9.dist-info/WHEEL
odoo_addon_maintenance_equipment_image-16.0.1.0.0.9.dist-info/top_level.txt
odoo_addon_maintenance_equipment_image-16.0.1.0.0.9.dist-info/RECORD
